tealeaf/__init__.py
tealeaf/__version__.py
tealeaf/core.py
tealeaf/headers.py
tealeaf-0.0.9.dist-info/METADATA
tealeaf-0.0.9.dist-info/WHEEL
tealeaf-0.0.9.dist-info/licenses/LICENSE
tealeaf-0.0.9.dist-info/RECORD
