Metadata-Version: 2.1
Name: tealeaf
Version: 0.0.9
Summary: An HTTP API client for readable code
Project-URL: Homepage, https://github.com/jackmuskopf/tealeaf
Project-URL: Bug Tracker, https://github.com/jackmuskopf/tealeaf/issues
Author-email: Jack Muskopf <jam.muskopf@gmail.com>
License-File: LICENSE
Classifier: License :: OSI Approved :: MIT License
Classifier: Operating System :: OS Independent
Classifier: Programming Language :: Python :: 3
Requires-Python: >=3.7
